shiba/__init__.py
shiba_dv-0.1.0.dist-info/METADATA
shiba_dv-0.1.0.dist-info/WHEEL
shiba_dv-0.1.0.dist-info/top_level.txt
shiba_dv-0.1.0.dist-info/RECORD
