Metadata-Version: 2.4
Name: shiba-dv
Version: 0.1.0
Summary: Linguaggio italiano stile Python
Author-email: Davide <davidix740@gmail.com>
License: MIT
